meter_models-0.2.0.dist-info/METADATA
meter_models-0.2.0.dist-info/WHEEL
meter_models-0.2.0.dist-info/entry_points.txt
meter_models/__init__.py
meter_models/manager.py
meter_models/schema.py
meter_models-0.2.0.dist-info/RECORD
