Metadata-Version: 2.1
Name: meter_models
Version: 0.2.0
Summary: Default template for PDM package
Author-Email: svtter <svtter@qq.com>
License: MIT
Requires-Python: >=3.9
Requires-Dist: pydantic>=2.10.5
Requires-Dist: psutil>=6.1.1
Requires-Dist: pyyaml>=6.0.2
